LICENSE
MANIFEST.in
README.md
etatimer.py
setup.py
etatimer.egg-info/PKG-INFO
etatimer.egg-info/SOURCES.txt
etatimer.egg-info/dependency_links.txt
etatimer.egg-info/requires.txt
etatimer.egg-info/top_level.txt