Metadata-Version: 1.1
Name: etatimer
Version: 0.0.3
Summary: Copyright (c) Charles LeDouxAll rights reserved.
Home-page: UNKNOWN
Author: Charles LeDoux
Author-email: charles.a.ledoux@gmail.com
License: MIT
Platform: UNKNOWN
Classifier: Development Status :: 4 - Beta
Classifier: Environment :: Console
Classifier: Intended Audience :: Developers
Classifier: License :: OSI Approved :: MIT License
Classifier: Operating System :: POSIX :: Linux
